neurovortex/__init__.py
neurovortex/model_loader.py
neurovortex/optimizer.py
neurovortex/resource_manager.py
neurovortex/utils.py
tests/__init__.py
tests/test_model_loader.py
tests/test_optimizer.py
tests/test_resource_manger.py
neurovortex-0.1.0.dist-info/METADATA
neurovortex-0.1.0.dist-info/WHEEL
neurovortex-0.1.0.dist-info/top_level.txt
neurovortex-0.1.0.dist-info/RECORD
